tap_adql_sandbox/__init__.py
tap_adql_sandbox/__main__.py
tap_adql_sandbox/examples.py
tap_adql_sandbox/theme.py
tap_adql_sandbox/version.py
tap_adql_sandbox/fonts/JetBrainsMono-Thin.ttf
tap_adql_sandbox/icons/planet-128.ico
tap_adql_sandbox/icons/planet-256.ico
tap_adql_sandbox-0.8.2.dist-info/LICENSE
tap_adql_sandbox-0.8.2.dist-info/METADATA
tap_adql_sandbox-0.8.2.dist-info/WHEEL
tap_adql_sandbox-0.8.2.dist-info/entry_points.txt
tap_adql_sandbox-0.8.2.dist-info/top_level.txt
tap_adql_sandbox-0.8.2.dist-info/RECORD
