Metadata-Version: 2.2
Name: tap-adql-sandbox
Version: 0.8.2
Summary: A sandbox application for executing ADQL queries via TAP interface
Home-page: https://github.com/retifrav/tap-adql-sandbox
Author: retif
Project-URL: Bug Tracker, https://github.com/retifrav/tap-adql-sandbox/issues
Project-URL: Changelog, https://github.com/retifrav/tap-adql-sandbox/blob/master/changelog.md
Keywords: tap,adql,gui,astronomy,astrophysics,cosmology,science
Classifier: Programming Language :: Python :: 3.6
Classifier: License :: OSI Approved :: GNU General Public License v3 (GPLv3)
Classifier: Operating System :: MacOS
Classifier: Operating System :: Microsoft :: Windows
Classifier: Operating System :: POSIX :: Linux
Classifier: Topic :: Desktop Environment
Classifier: Topic :: Software Development :: User Interfaces
Classifier: Topic :: Scientific/Engineering :: Astronomy
Classifier: Intended Audience :: Science/Research
Classifier: Intended Audience :: Education
Classifier: Intended Audience :: Developers
Requires-Python: >=3.6
License-File: LICENSE
Requires-Dist: dearpygui>=1.5.0
Requires-Dist: pyvo
Requires-Dist: astroquery
Requires-Dist: pandas
Requires-Dist: tabulate
